pristy/__init__.py
pristy/alfresco_operator/__init__.py
pristy/alfresco_operator/create_children_table.py
pristy/alfresco_operator/download_content_operator.py
pristy/alfresco_operator/fetch_children_node_operator.py
pristy/alfresco_operator/fetch_metadata_node_operator.py
pristy/alfresco_operator/fetch_node_exist_operator.py
pristy/alfresco_operator/fetch_node_operator.py
pristy/alfresco_operator/load_nodes_from_sqlite.py
pristy/alfresco_operator/push_node_to_directory.py
pristy/alfresco_operator/push_node_to_kafka.py
pristy/alfresco_operator/save_folder_to_db.py
pristy/alfresco_operator/save_node_to_sqlite.py
pristy/alfresco_operator/search_node_operator.py
pristy/alfresco_operator/transform_file.py
pristy/alfresco_operator/transform_folder.py
pristy/alfresco_operator/update_node_db.py
pristy/alfresco_operator/update_node_path.py
pristy/alfresco_operator/upload_pristy_operator.py
pristy/alfresco_operator/utils.py
pristy/schema/node_injector.schema.json
pristy/schema/node_injector.schema.json.license
pristy_alfresco_operators-0.8.1.dist-info/METADATA
pristy_alfresco_operators-0.8.1.dist-info/WHEEL
pristy_alfresco_operators-0.8.1.dist-info/RECORD
