Metadata-Version: 2.4
Name: pristy-alfresco-operators
Version: 0.8.1
Summary: Alfresco Operators for Pristy
Author-email: Jérémie Lesage <jeremie.lesage@jeci.fr>
License: Apache-2.0
Keywords: airflow,alfresco,pristy
Classifier: Development Status :: 5 - Production/Stable
Classifier: Framework :: Apache Airflow
Classifier: Framework :: Pytest
Classifier: Intended Audience :: Developers
Classifier: License :: OSI Approved :: Apache Software License
Classifier: Programming Language :: Python :: 3.12
Classifier: Topic :: Software Development :: Libraries
Requires-Python: <3.13,>=3.12
Requires-Dist: apache-airflow-providers-apache-kafka>=1.6.1
Requires-Dist: apache-airflow-providers-http>=4.13.3
Requires-Dist: apache-airflow-providers-postgres>=5.14.0
Requires-Dist: apache-airflow<4.0.0,>=3.1.2
Requires-Dist: jsonschema>=4.24.0
Requires-Dist: pendulum>=3.1.0
Requires-Dist: requests>=2.32.4
